[{"topic": "Messi scores as Miami wins rescheduled friendly", "score": 50.0, "factors": ["1 sources", "< 2h old", "high-value: messi"], "stories": [{"title": "Messi scores as Miami wins rescheduled friendly", "summary": "Inter Miami CF beat Independiente del Valle 2-1 on Thursday night in Puerto Rico with goals from Santiago Morales and Lionel Messi to conclude the team's preseason friendly tour.", "url": "https://www.espn.com/soccer/story/_/id/48049042/lionel-messi-scores-inter-miami-wins-rescheduled-friendly", "source": "ESPN FIFA", "source_type": "rss", "matched_keyword": "messi", "published_at": "2026-02-27 10:43:59", "story_hash": "dca0a96f6858524d"}], "sources": ["ESPN FIFA"], "top_url": "https://www.espn.com/soccer/story/_/id/48049042/lionel-messi-scores-inter-miami-wins-rescheduled-friendly", "matched_keyword": "messi", "story_count": 1}, {"topic": "Ronaldo buys 25% stake in Spanish club Almeria", "score": 50.0, "factors": ["1 sources", "< 2h old", "high-value: ronaldo"], "stories": [{"title": "Ronaldo buys 25% stake in Spanish club Almeria", "summary": "Cristiano Ronaldo has acquired a 25% ownership stake in Spanish second division club UD Almeria.", "url": "https://www.espn.com/soccer/story/_/id/48041207/cristiano-ronaldo-purchases-25-stake-spanish-club-almeria", "source": "ESPN FIFA", "source_type": "rss", "matched_keyword": "ronaldo", "published_at": "2026-02-27 10:43:58", "story_hash": "e710118fbcf89229"}], "sources": ["ESPN FIFA"], "top_url": "https://www.espn.com/soccer/story/_/id/48041207/cristiano-ronaldo-purchases-25-stake-spanish-club-almeria", "matched_keyword": "ronaldo", "story_count": 1, "story_hash": "e710118fbcf89229"}]